yoshi/__init__.py
yoshi/__main__.py
yoshi/account.py
yoshi/cli.py
yoshi/crypto.py
yoshi/database.py
yoshi/process.py
yoshi/wordlist.py
yoshi_cli-0.2.2.dist-info/licenses/LICENSE
yoshi_cli-0.2.2.dist-info/METADATA
yoshi_cli-0.2.2.dist-info/WHEEL
yoshi_cli-0.2.2.dist-info/entry_points.txt
yoshi_cli-0.2.2.dist-info/top_level.txt
yoshi_cli-0.2.2.dist-info/RECORD
