Metadata-Version: 2.4
Name: yoshi-cli
Version: 0.2.2
Summary: A password manager for the command line.
Author-email: Christian Cleberg <hello@cleberg.net>
Project-URL: Homepage, https://git.sr.ht/~cxc/yoshi-cli
Project-URL: Issues, https://git.sr.ht/~cxc/yoshi-cli
Classifier: Programming Language :: Python :: 3
Classifier: License :: OSI Approved :: GNU General Public License v3 (GPLv3)
Classifier: Operating System :: OS Independent
Requires-Python: >=3.8
License-File: LICENSE
Requires-Dist: cryptography
Requires-Dist: prettytable
Dynamic: license-file
